bwpy/__init__.py
bwpy/__main__.py
bwpy/bitwarden/__init__.py
bwpy/bitwarden/collection.py
bwpy/bitwarden/item.py
bwpy/bitwarden/org.py
bwpy/bwpy.py
bwpy/cli.py
bwpy/version.py
bwpy-0.1.8.dist-info/entry_points.txt
bwpy-0.1.8.dist-info/WHEEL
bwpy-0.1.8.dist-info/METADATA
bwpy-0.1.8.dist-info/RECORD
