Metadata-Version: 2.1
Name: bwpy
Version: 0.1.8
Summary: 
Author: Rob Wilson
Author-email: roobert@gmail.com
Requires-Python: >=3.7,<4.0
Classifier: Programming Language :: Python :: 3
Classifier: Programming Language :: Python :: 3.7
Classifier: Programming Language :: Python :: 3.8
Requires-Dist: sh (>=1.12.14,<2.0.0)
